<?xml version="1.0" encoding="utf-8"?>
<mvc:View
	controllerName="HTS.IT.FIAE.ITQ.controller.App"
	xmlns="sap.m"
	xmlns:mvc="sap.ui.core.mvc"
	displayBlock="true">
	<Shell backgroundColor="#CCCCCC" backgroundOpacity="0.5" logo="logo.png">
		<App>
			<pages>
				<Page title="{i18n>homePageTitle}">
					<content>
						<mvc:XMLView viewName="HTS.IT.FIAE.ITQ.view.Summe"/>
						<mvc:XMLView viewName="HTS.IT.FIAE.ITQ.view.List"/>
					</content>
				</Page>
			</pages>
		</App>
	</Shell>
</mvc:View>